{
    "id": "250114dd-abbe-481c-80d8-4080537c40c4",
    "body": {
        "_meta": {
            "name": "Main Navigation",
            "schema": "https://sfcc.com/site/navigation/root",
            "deliveryKey": "main-nav",
            "hierarchy": {
                "root": true
            }
        },
        "icon": {
            "_meta": {
                "schema": "http://bigcontent.io/cms/schema/v1/core#/definitions/image-link"
            },
            "id": "4ce65466-d87f-411b-afea-0fc38bbe0582",
            "name": "amplience-logo",
            "endpoint": "sfcccompdev",
            "defaultHost": "cdn.media.amplience.net"
        },
        "alt":"logo",
        "title": "Main Navigation",
        "description": "The main navigation that appears at the top of the page."
    },
    "version": 1,
    "label": "Main Navigation",
    "status": "ACTIVE",
    "createdBy": "fb90fd96-dcaf-4d67-9747-b9676282f661",
    "createdDate": "2022-08-18T15:19:48.726Z",
    "lastModifiedBy": "ec8eae46-fcfe-4c9f-8e2c-5a0f8aea334c",
    "lastModifiedDate": "2022-08-22T15:55:35.087Z",
    "lastPublishedVersion": 1,
    "lastPublishedDate": "2022-08-24T16:19:53.872Z",
    "hierarchy": {
        "root": true
    },
    "deliveryId": "250114dd-abbe-481c-80d8-4080537c40c4"
}